salespyforce/__init__.py
salespyforce/api.py
salespyforce/chatter.py
salespyforce/core.py
salespyforce/errors/__init__.py
salespyforce/errors/exceptions.py
salespyforce/errors/handlers.py
salespyforce/knowledge.py
salespyforce/utils/__init__.py
salespyforce/utils/core_utils.py
salespyforce/utils/helper.py
salespyforce/utils/log_utils.py
salespyforce/utils/tests/__init__.py
salespyforce/utils/tests/conftest.py
salespyforce/utils/tests/resources.py
salespyforce/utils/tests/test_core_utils.py
salespyforce/utils/tests/test_instantiate_object.py
salespyforce/utils/tests/test_log_utils.py
salespyforce/utils/tests/test_sobjects.py
salespyforce/utils/tests/test_soql.py
salespyforce/utils/tests/test_sosl.py
salespyforce/utils/tests/test_version_utils.py
salespyforce/utils/version.py
salespyforce-1.4.0.dev2.dist-info/LICENSE
salespyforce-1.4.0.dev2.dist-info/METADATA
salespyforce-1.4.0.dev2.dist-info/WHEEL
salespyforce-1.4.0.dev2.dist-info/RECORD
