Metadata-Version: 2.3
Name: salespyforce
Version: 1.4.0.dev2
Summary: A Python toolset for performing Salesforce API calls
License: MIT License
Keywords: salesforce,sfdc,api,rest,tooling,python
Author: Jeff Shurtliff
Author-email: jeffshurtliff@gmail.com
Requires-Python: >=3.9,<4.0
Classifier: Development Status :: 4 - Beta
Classifier: Intended Audience :: Developers
Classifier: License :: OSI Approved :: MIT License
Classifier: Programming Language :: Python :: 3
Classifier: Programming Language :: Python :: 3 :: Only
Classifier: Programming Language :: Python :: 3.9
Classifier: Programming Language :: Python :: 3.10
Classifier: Programming Language :: Python :: 3.11
Classifier: Programming Language :: Python :: 3.12
Classifier: Programming Language :: Python :: 3.13
Classifier: Topic :: Software Development :: Libraries
Classifier: Topic :: Internet :: WWW/HTTP
Requires-Dist: PyYAML (>=6.0.3,<7)
Requires-Dist: requests (>=2.32.5)
Project-URL: Documentation, https://salespyforce.readthedocs.io/en/latest/
Project-URL: Homepage, https://github.com/jeffshurtliff/salespyforce
Project-URL: Issue Tracker, https://github.com/jeffshurtliff/salespyforce/issues
Project-URL: Repository, https://github.com/jeffshurtliff/salespyforce
